windows_tools.antivirus-0.7.4-py3.11-nspkg.pth
windows_tools/antivirus/__init__.py
windows_tools.antivirus-0.7.4.dist-info/LICENSE
windows_tools.antivirus-0.7.4.dist-info/METADATA
windows_tools.antivirus-0.7.4.dist-info/WHEEL
windows_tools.antivirus-0.7.4.dist-info/namespace_packages.txt
windows_tools.antivirus-0.7.4.dist-info/top_level.txt
windows_tools.antivirus-0.7.4.dist-info/RECORD
