Metadata-Version: 2.1
Name: windows-tools.antivirus
Version: 0.7.4
Summary: antivirus state and installed products retrieval
Home-page: https://github.com/netinvent/windows_tools
Author: NetInvent - Orsiris de Jong
Author-email: contact@netinvent.fr
Keywords: wmi,virtualization,file,acl,ntfs,refs,antivirus,security,firewall,office
Classifier: Development Status :: 5 - Production/Stable
Classifier: Intended Audience :: Developers
Classifier: Topic :: Software Development
Classifier: Topic :: System
Classifier: Topic :: System :: Operating System
Classifier: Topic :: System :: Shells
Classifier: Programming Language :: Python
Classifier: Programming Language :: Python :: 3
Classifier: Programming Language :: Python :: Implementation :: CPython
Classifier: Programming Language :: Python :: Implementation :: PyPy
Classifier: Operating System :: Microsoft
Classifier: Operating System :: Microsoft :: Windows
Classifier: License :: OSI Approved :: BSD License
Requires-Python: >=3.5
License-File: LICENSE
Requires-Dist: windows-tools.installed-software (>=0.5.4)
Requires-Dist: windows-tools.wmi-queries (>=0.9.7)
Requires-Dist: typing (>=3.5.0)
